kindle_sdr_cleaner.py
kindle_sdr_cleaner-0.1.1.dist-info/entry_points.txt
kindle_sdr_cleaner-0.1.1.dist-info/LICENSE
kindle_sdr_cleaner-0.1.1.dist-info/WHEEL
kindle_sdr_cleaner-0.1.1.dist-info/METADATA
kindle_sdr_cleaner-0.1.1.dist-info/RECORD
