Metadata-Version: 2.1
Name: kindle-sdr-cleaner
Version: 0.1.1
Summary: Clean useless .sdr folders in your Kindle.
Home-page: https://github.com/whtsky/kindle-sdr-cleaner
License: MIT
Author: Wu Haotian
Author-email: whtsky@gmail.com
Requires-Python: >=3.6,<4.0
Classifier: License :: OSI Approved :: MIT License
Classifier: Programming Language :: Python :: 3
Classifier: Programming Language :: Python :: 3.6
Classifier: Programming Language :: Python :: 3.7
Classifier: Programming Language :: Python :: 3.8
Classifier: Programming Language :: Python :: 3.9
Project-URL: Repository, https://github.com/whtsky/kindle-sdr-cleaner
